beetsplug/alternatives.py
beets_alternatives-0.14.0.dist-info/METADATA
beets_alternatives-0.14.0.dist-info/WHEEL
beets_alternatives-0.14.0.dist-info/licenses/LICENSE
beets_alternatives-0.14.0.dist-info/RECORD
