Metadata-Version: 2.4
Name: beets-alternatives
Version: 0.14.0
Summary: beets plugin to manage multiple files
Project-URL: Homepage, http://www.github.com/geigerzaehler/beets-alternatives
Project-URL: Repository, http://www.github.com/geigerzaehler/beets-alternatives
Author-email: Thomas Scholtes <geigerzaehler@axiom.fm>, wisp3rwind <wisp3rwind@posteo.eu>
License-Expression: MIT
License-File: LICENSE
Classifier: Environment :: Console
Classifier: License :: OSI Approved :: MIT License
Classifier: Programming Language :: Python
Classifier: Topic :: Multimedia :: Sound/Audio
Classifier: Topic :: Multimedia :: Sound/Audio :: Players :: MP3
Requires-Python: >=3.10
Requires-Dist: beets<3,>=2.1.0
Requires-Dist: typing-extensions>=4.9.0
